{"id":"14510","name":"一袋烤可可豆 Sack of Roasted Cocoa Beans  - 3","transitionsToward":[{"actorID":"11847","targetID":"14511","newActorID":"235","newTargetID":"14510","hand":true},{"actorID":"235","targetID":"14509","newActorID":"14513","newTargetID":"14510","hand":true}],"transitionsAway":[{"actorID":"235","targetID":"14510","newActorID":"14513","newTargetID":"14511","hand":true},{"actorID":"11847","targetID":"14510","newActorID":"235","newTargetID":"14509","hand":true}],"transitionsTimed":[],"craftable":true,"depth":117,"size":2,"minPickupAge":3,"sounds":[1187],"techTree":[{"id":"11847","nodes":[{"id":"14172","nodes":[{"id":"235","nodes":[]},{"id":"14170","nodes":[]}]},{"id":"250","nodes":[{"decay":"15s"},{"id":"249","nodes":[]}]}]},{"id":"14511","nodes":[{"id":"11847","nodes":[{"id":"14172","nodes":[]},{"id":"250","nodes":[]}]},{"id":"14512","nodes":[{"id":"11847","nodes":[]},{"id":"7573","nodes":[]}]}]}],"recipe":{"steps":[[{"id":"6402","count":6,"uses":"x6","mainBranch":true,"depth":11,"targetID":"6411","hand":true}],[{"id":"12111","count":6,"uses":"x6","mainBranch":true,"depth":10,"actorID":"6402","targetID":"6400","hand":true}],[{"id":"12112","count":2,"uses":"x2","mainBranch":true,"depth":9,"actorID":"12111","targetID":"12111","hand":true}],[{"id":"6407","count":2,"uses":"x2","mainBranch":true,"depth":8,"actorID":"12111","targetID":"12112","hand":true}],[{"id":"6406","mainBranch":true,"depth":7,"actorID":"6407","targetID":"2682","hand":true}],[{"id":"6403","mainBranch":true,"depth":6,"actorID":"6407","targetID":"6406","hand":true}],[{"id":"6404","mainBranch":true,"depth":5,"actorID":"568","targetID":"6403","hand":true}],[{"id":"6405","mainBranch":true,"depth":4,"targetID":"6404","hand":true},{"id":"59","depth":4,"subSteps":[[{"id":"57","count":4,"uses":"x4","depth":6,"targetID":"50","hand":true}],[{"id":"58","count":2,"uses":"x2","depth":5,"actorID":"57","targetID":"57","hand":true}],[{"id":"59","depth":4,"actorID":"58","targetID":"58","hand":true}]]}],[{"id":"7573","mainBranch":true,"depth":3,"actorID":"59","targetID":"6405","hand":true},{"id":"11847","count":3,"uses":"x3","depth":3,"subSteps":[[{"id":"14172","count":3,"uses":"x3","depth":4,"actorID":"235","targetID":"14170","hand":true}],[{"id":"11847","count":3,"uses":"x3","depth":3,"actorID":"14172","targetID":"250","hand":true}]]}],[{"id":"14512","mainBranch":true,"depth":2,"actorID":"11847","targetID":"7573","hand":true}],[{"id":"14511","mainBranch":true,"depth":1,"actorID":"11847","targetID":"14512","hand":true}],[{"id":"14510","mainBranch":true,"depth":0,"actorID":"11847","targetID":"14511","hand":true}]],"ingredients":["2682","568","6400","14170","235","250","6411","50","50","50","50"]}}