{"id":"14720","name":"蓝色亚麻色调Blue Linen Tunic","transitionsToward":[{"actorID":"14724","targetID":"733","newActorID":"14720","newTargetID":"733","targetRemains":true,"hand":true}],"transitionsAway":[],"transitionsTimed":[],"craftable":false,"clothing":"t","insulation":0.12249999999999998,"size":2,"minPickupAge":3,"sounds":[941,286],"techTree":[{"id":"14724","nodes":[{"id":"14528","nodes":[{"decay":"5m"},{"id":"14724","nodes":[]}]},{"id":"731","nodes":[{"id":"729","nodes":null},{"id":"730","nodes":[]}]}]},{"id":"733","nodes":[{"id":"716","nodes":[{"id":"34","nodes":[]},{"id":"713","nodes":null}]},{"id":"730","nodes":[{"id":"382","nodes":[]},{"id":"85","nodes":[]}]}]}]}