{"id":"33888","name":"Flowering Pomelo Tree -  Bee Sweet Orange Paternal","transitionsToward":[{"actorID":"34139","targetID":"33883","newTargetID":"33888"}],"transitionsAway":[{"actorID":"33888","newActorID":"33891","newTargetID":"4569"},{"actorID":"568","targetID":"33888","newActorID":"33909","newTargetID":"33888","targetRemains":true,"hand":true}],"transitionsTimed":[{"targetID":"33888","newTargetID":"4569","decay":"2s","move":3}],"craftable":false,"insulation":0.4,"blocksWalking":true,"moveType":3,"moveDistance":1,"techTree":[{"id":"34139","nodes":[{"decay":"2s"},{"id":"34168","nodes":[{"id":"4567","nodes":[]},{"id":"34167","nodes":[]}]}]},{"id":"33883","nodes":[{"decay":"5m"},{"id":"33882","nodes":[{"decay":"5m"},{"id":"33881","nodes":[]}]}]}]}