{"id":"34455","name":"竹篁绿丝绸 -  1S","transitionsToward":[{"actorID":"4436","targetID":"34454","newActorID":"34455","newTargetID":"34454","targetRemains":true,"hand":true}],"transitionsAway":[{"actorID":"34455","targetID":"34456","newTargetID":"34457","hand":true},{"actorID":"34455","targetID":"34457","newTargetID":"34458","hand":true},{"actorID":"34455","targetID":"34458","newTargetID":"34459","hand":true}],"transitionsTimed":[],"craftable":false,"size":2,"minPickupAge":3,"sounds":[752],"techTree":[{"id":"4436","nodes":[{"id":"560","nodes":[{"id":"559","nodes":[]},{"id":"69","nodes":[]}]}]},{"id":"34454","nodes":null}]}