{"id":"34589","name":"Tabasco Turkey Slice on Plate -  +emotEat_26_10","transitionsToward":[{"actorID":"34587","newActorUses":"-1","targetID":"34588","newActorID":"34587","newTargetID":"34589","hand":true,"tool":true},{"actorID":"34587","actorUses":"last","targetID":"34588","newActorID":"235","newTargetID":"34589","hand":true}],"transitionsAway":[{"actorID":"34589","newActorID":"236","targetPlayer":true,"hand":true}],"transitionsTimed":[],"foodValue":[8,8],"craftable":false,"minPickupAge":3,"sounds":[352],"techTree":[{"id":"34587","nodes":[{"id":"235","nodes":[{"id":"283","nodes":[]}]},{"id":"34586","nodes":[{"decay":"2m"},{"id":"34585","nodes":[]}]}]},{"id":"34588","nodes":[{"id":"236","nodes":[{"id":"241","nodes":[]}]},{"id":"2187","nodes":[{"id":"11671","nodes":[]},{"id":"2186","nodes":[]}]}]}]}