{"id":"34673","name":"Filled Hole with Soil and Herbaceous Plant Seed","transitionsToward":[{"actorID":"34056","targetID":"25631","newTargetID":"34673","hand":true},{"actorID":"11634","newActorUses":"-1","newActorWeight":0.1,"targetID":"34086","newActorID":"11634","newTargetID":"34673","hand":true,"tool":true},{"actorID":"11634","actorUses":"last","targetID":"34086","newActorID":"11560","newTargetID":"34673","hand":true},{"actorID":"34057","newActorUses":"-1","targetID":"25631","newActorID":"34057","newTargetID":"34673","hand":true,"tool":true},{"actorID":"34057","actorUses":"last","targetID":"25631","newActorID":"7630","newTargetID":"34673","hand":true},{"actorID":"502","newActorUses":"-1","newActorWeight":0.05,"targetID":"34086","newActorID":"502","newTargetID":"34673","hand":true,"tool":true},{"actorID":"502","actorUses":"last","targetID":"34086","newActorID":"858","newTargetID":"34673","hand":true}],"transitionsAway":[{"targetID":"34673","newActorID":"34056","newTargetID":"25631","hand":true},{"actorID":"11634","newActorUses":"-1","newActorWeight":0.1,"targetID":"34673","newActorID":"11634","newTargetID":"34086","hand":true,"tool":true},{"actorID":"11634","actorUses":"last","targetID":"34673","newActorID":"11560","newTargetID":"34086","hand":true},{"actorID":"502","newActorUses":"-1","newActorWeight":0.05,"targetID":"34673","newActorID":"502","newTargetID":"34086","hand":true,"tool":true},{"actorID":"502","actorUses":"last","targetID":"34673","newActorID":"858","newTargetID":"34086","hand":true}],"transitionsTimed":[],"craftable":true,"depth":80,"techTree":[{"id":"34056","nodes":[{"id":"33899","nodes":[{"id":"33902","nodes":[]}]}]},{"id":"25631","nodes":[{"id":"336","nodes":[{"id":"292","nodes":[]},{"id":"211","nodes":null}]},{"id":"8725","nodes":[{"decay":"5m"},{"id":"8716","nodes":[]}]}]}],"recipe":{"steps":[[{"id":"486","depth":18,"actorID":"33","targetID":"107","hand":true}],[{"id":"8717","mainBranch":true,"depth":17,"actorID":"11634","targetID":"486","hand":true}],[{"id":"8716","mainBranch":true,"depth":16,"targetID":"8717","hand":true}],[{"id":"8725","mainBranch":true,"depth":15,"targetID":"8716","decay":"5m"},{"id":"382","count":2,"uses":"x2","depth":15,"actorID":"235","targetID":"141","hand":true}],[{"id":"25527","mainBranch":true,"depth":14,"actorID":"382","targetID":"8725","hand":true}],[{"id":"25632","mainBranch":true,"depth":13,"targetID":"25527","decay":"927s"}],[{"id":"25633","mainBranch":true,"depth":12,"actorID":"11634","targetID":"25632","hand":true}],[{"id":"25634","mainBranch":true,"depth":11,"actorID":"382","targetID":"25633","hand":true}],[{"id":"25528","mainBranch":true,"depth":10,"targetID":"25634","decay":"5m"},{"id":"227","count":3,"uses":"x3","depth":10,"subSteps":[[{"id":"224","count":3,"uses":"x3","depth":13,"actorID":"34","targetID":"242","hand":true}],[{"id":"225","count":3,"uses":"x3","depth":12,"targetID":"224","hand":true}],[{"id":"226","count":3,"uses":"x3","depth":11,"actorID":"64","targetID":"225","hand":true}],[{"id":"227","count":3,"uses":"x3","depth":10,"targetID":"226","hand":true}]]}],[{"id":"33870","uses":"max","mainBranch":true,"depth":9,"actorID":"227","actorUses":"x3","targetID":"25528","hand":true}],[{"id":"33871","uses":"max","mainBranch":true,"depth":8,"actorID":"248","targetID":"33870","targetUses":"max","hand":true}],[{"id":"33874","mainBranch":true,"depth":7,"targetID":"33871","targetUses":"max","decay":"90s"}],[{"id":"33875","mainBranch":true,"depth":6,"actorID":"660","targetID":"33874","hand":true}],[{"id":"33876","mainBranch":true,"depth":5,"targetID":"33875","weight":0.5,"decay":"5m"}],[{"id":"33901","mainBranch":true,"depth":4,"actorID":"11634","targetID":"33876","hand":true}],[{"id":"33902","mainBranch":true,"depth":3,"actorID":"8712","targetID":"33901","hand":true}],[{"id":"33899","mainBranch":true,"depth":2,"targetID":"33902","hand":true}],[{"id":"34056","mainBranch":true,"depth":1,"targetID":"33899","hand":true}],[{"id":"34673","mainBranch":true,"depth":0,"actorID":"34056","targetID":"25631","hand":true}]],"ingredients":["660","25631","11634","8712","235","248","107","34","64","141","33","242","242","242"]}}